orbital_visualizator/__init__.py
orbital_visualizator/gui_orbital_visualizator.py
orbital_visualizator/keplerian_to_cartesian_convertor.py
orbital_visualizator/orbital_visualizator_app.py
orbital_visualizator/plot_orbital_visualizator.py
Orbital_Visualizator-0.1.dist-info/METADATA
Orbital_Visualizator-0.1.dist-info/WHEEL
Orbital_Visualizator-0.1.dist-info/top_level.txt
Orbital_Visualizator-0.1.dist-info/RECORD
